{
    "days": {
      "word": ["monday", "tuesday"],
      "number": ["2024-02-19", "2024-02-20"]
    },
    "datasets": [
      {
        "label": "Sleep",
        "data": [
          {
            "x": ["00:00", "08:00"],
            "y": "2024-02-19"
          },
          {
            "x": ["20:00", "24:00"],
            "y": "2024-02-19"
          },
          {
            "x": ["00:00", "09:00"],
            "y": "2024-02-19"
          },
          {
            "x": ["21:00", "24:00"],
            "y": "2024-02-19"
          }
        ],
        "backgroundColor": "rgba(255, 26, 104, 0.2)",
        "borderColor": "rgba(255, 26, 104, 1)",
        "borderWidth": 1
      },
      {
        "label": "Class",
        "data": [
          {
            "x": [
              "08:00",
              "15:00"
            ],
            "y": "2024-02-19"
          },
          {
            "x": [
              "09:00",
              "16:00"
            ],
            "y": "2024-02-20"
          }
        ],
        "backgroundColor": "rgba(255, 26, 104, 0.2)",
        "borderColor": "rgba(255, 26, 104, 1)",
        "borderWidth": 1
      },
      {
        "label": "Homework",
        "data": [
          {
            "x": ["15:00", "20:00"],
            "y": "2024-02-19"
          },
          {
            "x": ["16:00", "21:00"],
            "y": "2024-02-19"
          }
        ],
        "backgroundColor": "rgba(255, 26, 104, 0.2)",
        "borderColor": "rgba(255, 26, 104, 1)",
        "borderWidth": 1
      }
    ]
}